gnssr/__init__.py
gnssr/cygnss.py
gnssr-0.0.8.dist-info/LICENSE.txt
gnssr-0.0.8.dist-info/METADATA
gnssr-0.0.8.dist-info/WHEEL
gnssr-0.0.8.dist-info/top_level.txt
gnssr-0.0.8.dist-info/RECORD
