Metadata-Version: 2.1
Name: gnssr
Version: 0.0.8
Summary: GNSS-R Data Processing Package
Home-page: https://github.com/QinyuGuo-Pot/gnssr
Author: Qinyu Guo
Author-email: qinyuguo@chd.edu.cn
Requires-Python: >=3.6
License-File: LICENSE.txt
Requires-Dist: xarray
Requires-Dist: numpy
Requires-Dist: pandas
Requires-Dist: netcdf4
Requires-Dist: scipy
Requires-Dist: rasterio
Requires-Dist: matplotlib
Requires-Dist: jupyter
Requires-Dist: dask
Requires-Dist: geopandas
Requires-Dist: tqdm
